{
  "directed": true,
  "multigraph": false,
  "graph": {
    "session_id": "1766549770",
    "original_query": "What data do I have about DLF in local storage?",
    "file_manifest": [],
    "created_at": "2025-12-24T04:16:10.955129",
    "status": "running",
    "globals_schema": {
      "potential_storage_locations_T001": []
    }
  },
  "nodes": [
    {
      "description": "Initial Query",
      "agent": "System",
      "status": "completed",
      "output": null,
      "error": null,
      "cost": 0.0,
      "start_time": null,
      "end_time": null,
      "execution_time": 0.0,
      "id": "ROOT"
    },
    {
      "id": "Query",
      "description": "Formulate execution plan",
      "agent": "PlannerAgent",
      "status": "completed",
      "reads": [
        "original_query"
      ],
      "writes": [
        "plan_graph"
      ],
      "output": {
        "plan_graph": {
          "nodes": [
            {
              "id": "T001",
              "description": "Identify potential local storage locations.",
              "agent": "CoderAgent",
              "agent_prompt": "Write a Python script to identify potential local storage locations on the user's system, such as browser storage (cookies, localStorage, sessionStorage), application data directories, and common file storage locations. The script should generate a list of these locations and their descriptions.",
              "reads": [],
              "writes": [
                "potential_storage_locations_T001"
              ]
            },
            {
              "id": "T002",
              "description": "Check for DLF-related data in browser storage.",
              "agent": "CoderAgent",
              "agent_prompt": "Write a Python script using Selenium to check for the presence of data related to 'DLF' in the cookies, localStorage, and sessionStorage of the user's default web browser. The script should iterate through each domain and check for keys or values containing 'DLF'.  Log any found data, including the domain, storage type (cookie, localStorage, sessionStorage), key, and value.",
              "reads": [
                "potential_storage_locations_T001"
              ],
              "writes": [
                "browser_storage_dlf_data_T002"
              ]
            },
            {
              "id": "T003",
              "description": "Check for DLF-related data in application data directories.",
              "agent": "CoderAgent",
              "agent_prompt": "Write a Python script to search for files or directories containing 'DLF' within the application data directories identified in `potential_storage_locations_T001`. The script should recursively search these directories and log the path of any files or directories containing 'DLF' in their name or content.",
              "reads": [
                "potential_storage_locations_T001"
              ],
              "writes": [
                "application_data_dlf_data_T003"
              ]
            },
            {
              "id": "T004",
              "description": "Check for DLF-related data in common file storage locations.",
              "agent": "CoderAgent",
              "agent_prompt": "Write a Python script to search for files containing 'DLF' in common file storage locations identified in `potential_storage_locations_T001`, such as the user's Documents, Downloads, and Desktop folders.  The script should log the path of any files containing 'DLF' in their name or content.",
              "reads": [
                "potential_storage_locations_T001"
              ],
              "writes": [
                "common_file_storage_dlf_data_T004"
              ]
            },
            {
              "id": "T005",
              "description": "Summarize the DLF data found in local storage.",
              "agent": "DistillerAgent",
              "agent_prompt": "Summarize the DLF data found in browser storage from `browser_storage_dlf_data_T002`, application data directories from `application_data_dlf_data_T003`, and common file storage locations from `common_file_storage_dlf_data_T004`.  Provide a concise overview of where DLF-related data was found and the type of data identified in each location.",
              "reads": [
                "browser_storage_dlf_data_T002",
                "application_data_dlf_data_T003",
                "common_file_storage_dlf_data_T004"
              ],
              "writes": [
                "dlf_data_summary_T005"
              ]
            },
            {
              "id": "T006",
              "description": "Format the DLF data summary for presentation.",
              "agent": "FormatterAgent",
              "agent_prompt": "Format the DLF data summary from `dlf_data_summary_T005` into a human-readable Markdown report. The report should include clear headings for each storage location (browser, application data, common files) and a concise summary of the DLF-related data found in each location. Use bullet points or lists to present the information in an organized manner.",
              "reads": [
                "dlf_data_summary_T005"
              ],
              "writes": [
                "formatted_dlf_data_report_T006"
              ]
            }
          ],
          "edges": [
            {
              "source": "ROOT",
              "target": "T001"
            },
            {
              "source": "T001",
              "target": "T002"
            },
            {
              "source": "T001",
              "target": "T003"
            },
            {
              "source": "T001",
              "target": "T004"
            },
            {
              "source": "T002",
              "target": "T005"
            },
            {
              "source": "T003",
              "target": "T005"
            },
            {
              "source": "T004",
              "target": "T005"
            },
            {
              "source": "T005",
              "target": "T006"
            }
          ]
        },
        "next_step_id": "T007",
        "cost": 0.0002552,
        "input_tokens": 28,
        "output_tokens": 631,
        "total_tokens": 659
      },
      "error": null,
      "cost": 0.0,
      "start_time": null,
      "end_time": "2025-12-24T04:16:19.552130",
      "execution_time": 0.0
    },
    {
      "id": "T001",
      "description": "Identify potential local storage locations.",
      "agent": "CoderAgent",
      "agent_prompt": "Write a Python script to identify potential local storage locations on the user's system, such as browser storage (cookies, localStorage, sessionStorage), application data directories, and common file storage locations. The script should generate a list of these locations and their descriptions.",
      "reads": [],
      "writes": [
        "potential_storage_locations_T001"
      ],
      "status": "completed",
      "output": {
        "code_variants": {
          "CODE_1A": "import os\nimport platform\n\ndef get_platform():\n    return platform.system()\n\ndef get_appdata_location():\n    platform_name = get_platform()\n    if platform_name == \"Windows\":\n        return os.environ.get('APPDATA')\n    elif platform_name == \"Darwin\":\n        return os.path.join(os.path.expanduser('~'), 'Library', 'Application Support')\n    elif platform_name == \"Linux\":\n        return os.path.join(os.path.expanduser('~'), '.local', 'share')\n    else:\n        return None\n\n\ndef get_storage_locations():\n    locations = []\n\n    # Browser Storage\n    locations.append({\"path\": os.path.join(os.path.expanduser('~'), '.config', 'chromium', 'Default', 'Local Storage', 'leveldb'), \"description\": \"Chrome Local Storage\"})\n    locations.append({\"path\": os.path.join(os.path.expanduser('~'), '.mozilla', 'firefox'), \"description\": \"Firefox Profile Directory (Cookies, LocalStorage, etc.)\"})\n    locations.append({\"path\": os.path.join(os.path.expanduser('~'), 'Library', 'Cookies'), \"description\": \"Safari Cookies (macOS)\"})\n\n    # Application Data\n    appdata_location = get_appdata_location()\n    if appdata_location:\n        locations.append({\"path\": appdata_location, \"description\": \"Application Data Directory\"})\n\n    # Common File Storage\n    locations.append({\"path\": os.path.expanduser('~'), \"description\": \"User Home Directory (Documents, Downloads, etc.)\"})\n    locations.append({\"path\": os.path.join(os.path.expanduser('~'), 'Desktop'), \"description\": \"User Desktop\"})\n\n    return locations\n\nstorage_locations = get_storage_locations()\n\nreturn {\"potential_storage_locations_T001\": storage_locations}\n"
        },
        "cost": 7.630000000000001e-05,
        "input_tokens": 75,
        "output_tokens": 172,
        "total_tokens": 247,
        "execution_result": null,
        "execution_status": "error",
        "execution_error": "Too many functions (24 > 20)",
        "execution_time": "2025-12-24 09:46:23",
        "executed_variant": "CODE_1A",
        "execution_logs": null
      },
      "error": null,
      "cost": 7.630000000000001e-05,
      "start_time": "2025-12-24T04:16:19.560770",
      "end_time": "2025-12-24T04:16:23.768837",
      "execution_time": 4.208067,
      "iterations": [
        {
          "iteration": 1,
          "output": {
            "code_variants": {
              "CODE_1A": "import os\nimport platform\n\ndef get_platform():\n    return platform.system()\n\ndef get_appdata_location():\n    platform_name = get_platform()\n    if platform_name == \"Windows\":\n        return os.environ.get('APPDATA')\n    elif platform_name == \"Darwin\":\n        return os.path.join(os.path.expanduser('~'), 'Library', 'Application Support')\n    elif platform_name == \"Linux\":\n        return os.path.join(os.path.expanduser('~'), '.local', 'share')\n    else:\n        return None\n\n\ndef get_storage_locations():\n    locations = []\n\n    # Browser Storage\n    locations.append({\"path\": os.path.join(os.path.expanduser('~'), '.config', 'chromium', 'Default', 'Local Storage', 'leveldb'), \"description\": \"Chrome Local Storage\"})\n    locations.append({\"path\": os.path.join(os.path.expanduser('~'), '.mozilla', 'firefox'), \"description\": \"Firefox Profile Directory (Cookies, LocalStorage, etc.)\"})\n    locations.append({\"path\": os.path.join(os.path.expanduser('~'), 'Library', 'Cookies'), \"description\": \"Safari Cookies (macOS)\"})\n\n    # Application Data\n    appdata_location = get_appdata_location()\n    if appdata_location:\n        locations.append({\"path\": appdata_location, \"description\": \"Application Data Directory\"})\n\n    # Common File Storage\n    locations.append({\"path\": os.path.expanduser('~'), \"description\": \"User Home Directory (Documents, Downloads, etc.)\"})\n    locations.append({\"path\": os.path.join(os.path.expanduser('~'), 'Desktop'), \"description\": \"User Desktop\"})\n\n    return locations\n\nstorage_locations = get_storage_locations()\n\nreturn {\"potential_storage_locations_T001\": storage_locations}\n"
            },
            "cost": 7.630000000000001e-05,
            "input_tokens": 75,
            "output_tokens": 172,
            "total_tokens": 247
          }
        }
      ],
      "input_tokens": 75,
      "output_tokens": 172,
      "total_tokens": 247
    },
    {
      "id": "T002",
      "description": "Check for DLF-related data in browser storage.",
      "agent": "CoderAgent",
      "agent_prompt": "Write a Python script using Selenium to check for the presence of data related to 'DLF' in the cookies, localStorage, and sessionStorage of the user's default web browser. The script should iterate through each domain and check for keys or values containing 'DLF'.  Log any found data, including the domain, storage type (cookie, localStorage, sessionStorage), key, and value.",
      "reads": [
        "potential_storage_locations_T001"
      ],
      "writes": [
        "browser_storage_dlf_data_T002"
      ],
      "status": "running",
      "output": null,
      "error": null,
      "cost": 0.0,
      "start_time": "2025-12-24T04:16:23.778236",
      "end_time": null,
      "execution_time": 0.0
    },
    {
      "id": "T003",
      "description": "Check for DLF-related data in application data directories.",
      "agent": "CoderAgent",
      "agent_prompt": "Write a Python script to search for files or directories containing 'DLF' within the application data directories identified in `potential_storage_locations_T001`. The script should recursively search these directories and log the path of any files or directories containing 'DLF' in their name or content.",
      "reads": [
        "potential_storage_locations_T001"
      ],
      "writes": [
        "application_data_dlf_data_T003"
      ],
      "status": "running",
      "output": null,
      "error": null,
      "cost": 0.0,
      "start_time": "2025-12-24T04:16:23.779505",
      "end_time": null,
      "execution_time": 0.0
    },
    {
      "id": "T004",
      "description": "Check for DLF-related data in common file storage locations.",
      "agent": "CoderAgent",
      "agent_prompt": "Write a Python script to search for files containing 'DLF' in common file storage locations identified in `potential_storage_locations_T001`, such as the user's Documents, Downloads, and Desktop folders.  The script should log the path of any files containing 'DLF' in their name or content.",
      "reads": [
        "potential_storage_locations_T001"
      ],
      "writes": [
        "common_file_storage_dlf_data_T004"
      ],
      "status": "running",
      "output": null,
      "error": null,
      "cost": 0.0,
      "start_time": "2025-12-24T04:16:23.780729",
      "end_time": null,
      "execution_time": 0.0
    },
    {
      "id": "T005",
      "description": "Summarize the DLF data found in local storage.",
      "agent": "DistillerAgent",
      "agent_prompt": "Summarize the DLF data found in browser storage from `browser_storage_dlf_data_T002`, application data directories from `application_data_dlf_data_T003`, and common file storage locations from `common_file_storage_dlf_data_T004`.  Provide a concise overview of where DLF-related data was found and the type of data identified in each location.",
      "reads": [
        "browser_storage_dlf_data_T002",
        "application_data_dlf_data_T003",
        "common_file_storage_dlf_data_T004"
      ],
      "writes": [
        "dlf_data_summary_T005"
      ],
      "status": "pending",
      "output": null,
      "error": null,
      "cost": 0.0,
      "start_time": null,
      "end_time": null,
      "execution_time": 0.0
    },
    {
      "id": "T006",
      "description": "Format the DLF data summary for presentation.",
      "agent": "FormatterAgent",
      "agent_prompt": "Format the DLF data summary from `dlf_data_summary_T005` into a human-readable Markdown report. The report should include clear headings for each storage location (browser, application data, common files) and a concise summary of the DLF-related data found in each location. Use bullet points or lists to present the information in an organized manner.",
      "reads": [
        "dlf_data_summary_T005"
      ],
      "writes": [
        "formatted_dlf_data_report_T006"
      ],
      "status": "pending",
      "output": null,
      "error": null,
      "cost": 0.0,
      "start_time": null,
      "end_time": null,
      "execution_time": 0.0
    }
  ],
  "links": [
    {
      "source": "ROOT",
      "target": "Query"
    },
    {
      "source": "Query",
      "target": "T001"
    },
    {
      "source": "T001",
      "target": "T002"
    },
    {
      "source": "T001",
      "target": "T003"
    },
    {
      "source": "T001",
      "target": "T004"
    },
    {
      "source": "T002",
      "target": "T005"
    },
    {
      "source": "T003",
      "target": "T005"
    },
    {
      "source": "T004",
      "target": "T005"
    },
    {
      "source": "T005",
      "target": "T006"
    }
  ]
}